jaix/__init__.py
jaix/environment_factory.py
jaix/experiment.py
jaix/env/__init__.py
jaix/env/composite/__init__.py
jaix/env/composite/composite_environment.py
jaix/env/composite/switching_environment.py
jaix/env/singular/__init__.py
jaix/env/singular/ec_env.py
jaix/env/singular/hpo_env.py
jaix/env/singular/ljclust_env.py
jaix/env/singular/mastermind_env.py
jaix/env/singular/singular_environment.py
jaix/env/utils/__init__.py
jaix/env/utils/cocopp_testbed.py
jaix/env/utils/ase/__init__.py
jaix/env/utils/ase/ljclust_adapter.py
jaix/env/utils/hpo/__init__.py
jaix/env/utils/hpo/tabrepo_adapter.py
jaix/env/utils/problem/__init__.py
jaix/env/utils/problem/rbf_fit.py
jaix/env/utils/problem/sphere.py
jaix/env/utils/problem/static_problem.py
jaix/env/utils/problem/rbf/__init__.py
jaix/env/utils/problem/rbf/rbf.py
jaix/env/utils/problem/rbf/rbf_adapter.py
jaix/env/utils/switching_pattern/__init__.py
jaix/env/utils/switching_pattern/switching_pattern.py
jaix/env/wrapper/__init__.py
jaix/env/wrapper/auto_reset_wrapper.py
jaix/env/wrapper/closing_wrapper.py
jaix/env/wrapper/coco_logger_wrapper.py
jaix/env/wrapper/improvement_reward_wrapper.py
jaix/env/wrapper/max_eval_wrapper.py
jaix/env/wrapper/online_wrapper.py
jaix/env/wrapper/passthrough_wrapper.py
jaix/env/wrapper/value_track_wrapper.py
jaix/env/wrapper/wandb_wrapper.py
jaix/env/wrapper/wrapped_env_factory.py
jaix/runner/__init__.py
jaix/runner/optimiser.py
jaix/runner/runner.py
jaix/runner/ask_tell/__init__.py
jaix/runner/ask_tell/ask_tell_runner.py
jaix/runner/ask_tell/at_optimiser.py
jaix/runner/ask_tell/at_strategy.py
jaix/runner/ask_tell/strategy/__init__.py
jaix/runner/ask_tell/strategy/bandit.py
jaix/runner/ask_tell/strategy/basic_ea.py
jaix/runner/ask_tell/strategy/cma.py
jaix/runner/ask_tell/strategy/enumerate.py
jaix/runner/ask_tell/strategy/random.py
jaix/runner/ask_tell/strategy/utils/__init__.py
jaix/runner/ask_tell/strategy/utils/bandit_model.py
jaix/runner/ask_tell/strategy/utils/ea_utils.py
tai_jaix-0.1.1.58.dist-info/licenses/LICENSE
tai_jaix-0.1.1.58.dist-info/METADATA
tai_jaix-0.1.1.58.dist-info/WHEEL
tai_jaix-0.1.1.58.dist-info/top_level.txt
tai_jaix-0.1.1.58.dist-info/RECORD
