Metadata-Version: 2.4
Name: tai_jaix
Version: 0.1.1.58
License: GPL3
License-File: LICENSE
Requires-Dist: cma
Requires-Dist: gymnasium
Requires-Dist: tai-ttex
Requires-Dist: cocopp
Provides-Extra: ase
Requires-Dist: ase; extra == "ase"
Requires-Dist: kimpy; extra == "ase"
Requires-Dist: requests; extra == "ase"
Provides-Extra: tabrepo
Requires-Dist: tabrepo; extra == "tabrepo"
Requires-Dist: regex; extra == "tabrepo"
Provides-Extra: coco
Requires-Dist: coco-experiment; extra == "coco"
Requires-Dist: regex; extra == "coco"
Provides-Extra: test
Requires-Dist: pytest; extra == "test"
Requires-Dist: mypy; extra == "test"
Requires-Dist: pylint; extra == "test"
Requires-Dist: black; extra == "test"
Dynamic: description
Dynamic: description-content-type
Dynamic: license
Dynamic: license-file
Dynamic: provides-extra
Dynamic: requires-dist
